Workbook

Sheet Dashboard
A1: Ameya Heights — Roadmap Progress
A2: Live. Every figure is a formula over the Roadmap tab; it updates as you change Status.
A4: TOTAL ACTIONS | C4: DONE | E4: IN PROGRESS | G4: P1 OUTSTANDING
A5: =COUNTA(Roadmap!$A$5:$A$39) | C5: =COUNTIF(Roadmap!$I$5:$I$39,"Done") | E5: =COUNTIF(Roadmap!$I$5:$I$39,"In progress") | G5: =COUNTIFS(Roadmap!$H$5:$H$39,"P1",Roadmap!$I$5:$I$39,"<>Done")
A7: COMPLETION | C7: EFFORT REMAINING (HOURS) | E7: EFFORT DONE (HOURS) | G7: BLOCKED
A8: =IFERROR(COUNTIF(Roadmap!$I$5:$I$39,"Done")/COUNTA(Roadmap!$A$5:$A$39),0) | C8: =SUMIFS(Roadmap!$G$5:$G$39,Roadmap!$I$5:$I$39,"<>Done") | E8: =SUMIFS(Roadmap!$G$5:$G$39,Roadmap!$I$5:$I$39,"Done") | G8: =COUNTIF(Roadmap!$I$5:$I$39,"Blocked")
A11: BY HORIZON
A12: Horizon | B12: Total | C12: Done | D12: Remaining | E12: Hours left | F12: % done
A13: Done · v13 | B13: =COUNTIF(Roadmap!$B$5:$B$39,$A13) | C13: =COUNTIFS(Roadmap!$B$5:$B$39,$A13,Roadmap!$I$5:$I$39,"Done") | D13: =B13-C13 | E13: =SUMIFS(Roadmap!$G$5:$G$39,Roadmap!$B$5:$B$39,$A13,Roadmap!$I$5:$I$39,"<>Done") | F13: =IFERROR(C13/B13,0)
A14: H1 · Stabilise | B14: =COUNTIF(Roadmap!$B$5:$B$39,$A14) | C14: =COUNTIFS(Roadmap!$B$5:$B$39,$A14,Roadmap!$I$5:$I$39,"Done") | D14: =B14-C14 | E14: =SUMIFS(Roadmap!$G$5:$G$39,Roadmap!$B$5:$B$39,$A14,Roadmap!$I$5:$I$39,"<>Done") | F14: =IFERROR(C14/B14,0)
A15: H2 · Instrument | B15: =COUNTIF(Roadmap!$B$5:$B$39,$A15) | C15: =COUNTIFS(Roadmap!$B$5:$B$39,$A15,Roadmap!$I$5:$I$39,"Done") | D15: =B15-C15 | E15: =SUMIFS(Roadmap!$G$5:$G$39,Roadmap!$B$5:$B$39,$A15,Roadmap!$I$5:$I$39,"<>Done") | F15: =IFERROR(C15/B15,0)
A16: H3 · Compound | B16: =COUNTIF(Roadmap!$B$5:$B$39,$A16) | C16: =COUNTIFS(Roadmap!$B$5:$B$39,$A16,Roadmap!$I$5:$I$39,"Done") | D16: =B16-C16 | E16: =SUMIFS(Roadmap!$G$5:$G$39,Roadmap!$B$5:$B$39,$A16,Roadmap!$I$5:$I$39,"<>Done") | F16: =IFERROR(C16/B16,0)
A19: BY WORKSTREAM
A20: Workstream | B20: Total | C20: Done | D20: Hours left
A21: AI | B21: =COUNTIF(Roadmap!$C$5:$C$39,$A21) | C21: =COUNTIFS(Roadmap!$C$5:$C$39,$A21,Roadmap!$I$5:$I$39,"Done") | D21: =SUMIFS(Roadmap!$G$5:$G$39,Roadmap!$C$5:$C$39,$A21,Roadmap!$I$5:$I$39,"<>Done")
A22: AI continuity | B22: =COUNTIF(Roadmap!$C$5:$C$39,$A22) | C22: =COUNTIFS(Roadmap!$C$5:$C$39,$A22,Roadmap!$I$5:$I$39,"Done") | D22: =SUMIFS(Roadmap!$G$5:$G$39,Roadmap!$C$5:$C$39,$A22,Roadmap!$I$5:$I$39,"<>Done")
A23: Accessibility | B23: =COUNTIF(Roadmap!$C$5:$C$39,$A23) | C23: =COUNTIFS(Roadmap!$C$5:$C$39,$A23,Roadmap!$I$5:$I$39,"Done") | D23: =SUMIFS(Roadmap!$G$5:$G$39,Roadmap!$C$5:$C$39,$A23,Roadmap!$I$5:$I$39,"<>Done")
A24: Analytics | B24: =COUNTIF(Roadmap!$C$5:$C$39,$A24) | C24: =COUNTIFS(Roadmap!$C$5:$C$39,$A24,Roadmap!$I$5:$I$39,"Done") | D24: =SUMIFS(Roadmap!$G$5:$G$39,Roadmap!$C$5:$C$39,$A24,Roadmap!$I$5:$I$39,"<>Done")
A25: Channels | B25: =COUNTIF(Roadmap!$C$5:$C$39,$A25) | C25: =COUNTIFS(Roadmap!$C$5:$C$39,$A25,Roadmap!$I$5:$I$39,"Done") | D25: =SUMIFS(Roadmap!$G$5:$G$39,Roadmap!$C$5:$C$39,$A25,Roadmap!$I$5:$I$39,"<>Done")
A26: Code quality | B26: =COUNTIF(Roadmap!$C$5:$C$39,$A26) | C26: =COUNTIFS(Roadmap!$C$5:$C$39,$A26,Roadmap!$I$5:$I$39,"Done") | D26: =SUMIFS(Roadmap!$G$5:$G$39,Roadmap!$C$5:$C$39,$A26,Roadmap!$I$5:$I$39,"<>Done")
A27: Compliance | B27: =COUNTIF(Roadmap!$C$5:$C$39,$A27) | C27: =COUNTIFS(Roadmap!$C$5:$C$39,$A27,Roadmap!$I$5:$I$39,"Done") | D27: =SUMIFS(Roadmap!$G$5:$G$39,Roadmap!$C$5:$C$39,$A27,Roadmap!$I$5:$I$39,"<>Done")
A28: Content | B28: =COUNTIF(Roadmap!$C$5:$C$39,$A28) | C28: =COUNTIFS(Roadmap!$C$5:$C$39,$A28,Roadmap!$I$5:$I$39,"Done") | D28: =SUMIFS(Roadmap!$G$5:$G$39,Roadmap!$C$5:$C$39,$A28,Roadmap!$I$5:$I$39,"<>Done")
A29: Deploy | B29: =COUNTIF(Roadmap!$C$5:$C$39,$A29) | C29: =COUNTIFS(Roadmap!$C$5:$C$39,$A29,Roadmap!$I$5:$I$39,"Done") | D29: =SUMIFS(Roadmap!$G$5:$G$39,Roadmap!$C$5:$C$39,$A29,Roadmap!$I$5:$I$39,"<>Done")
A30: Engineering | B30: =COUNTIF(Roadmap!$C$5:$C$39,$A30) | C30: =COUNTIFS(Roadmap!$C$5:$C$39,$A30,Roadmap!$I$5:$I$39,"Done") | D30: =SUMIFS(Roadmap!$G$5:$G$39,Roadmap!$C$5:$C$39,$A30,Roadmap!$I$5:$I$39,"<>Done")
A31: Growth | B31: =COUNTIF(Roadmap!$C$5:$C$39,$A31) | C31: =COUNTIFS(Roadmap!$C$5:$C$39,$A31,Roadmap!$I$5:$I$39,"Done") | D31: =SUMIFS(Roadmap!$G$5:$G$39,Roadmap!$C$5:$C$39,$A31,Roadmap!$I$5:$I$39,"<>Done")
A32: Hygiene | B32: =COUNTIF(Roadmap!$C$5:$C$39,$A32) | C32: =COUNTIFS(Roadmap!$C$5:$C$39,$A32,Roadmap!$I$5:$I$39,"Done") | D32: =SUMIFS(Roadmap!$G$5:$G$39,Roadmap!$C$5:$C$39,$A32,Roadmap!$I$5:$I$39,"<>Done")
... A38: Security | B38: =COUNTIF(Roadmap!$C$5:$C$39,$A38) | C38: =COUNTIFS(Roadmap!$C$5:$C$39,$A38,Roadmap!$I$5:$I$39,"Done") | D38: =SUMIFS(Roadmap!$G$5:$G$39,Roadmap!$C$5:$C$39,$A38,Roadmap!$I$5:$I$39,"<>Done")

Sheet Roadmap
A1: Ameya Heights — Digital Roadmap Tracker
A2: Execution tracker for the enterprise audit. Change only the yellow columns (Status, Owner, Target date, Notes) — everything else recalculates.
A4: ID | B4: Horizon | C4: Workstream | D4: Action | E4: Why it matters | F4: Owner | G4: Effort (h) | H4: Priority | I4: Status | J4: Blocked by | K4: Target date | L4: Notes
A5: A1 | B5: Done · v13 | C5: Hygiene | D5: Delete 7 scratch HTML files from the deploy root | E5: Draft files were publicly reachable, not in sitemap, no noindex | F5: Claude | G5: 0.2 | H5: P1 | I5: Done
A6: A2 | B6: Done · v13 | C6: Hygiene | D6: Add Disallow rules to robots.txt (/_ , /api/, widget) | E6: Belt-and-braces against crawling internal fragments | F6: Claude | G6: 0.1 | H6: P2 | I6: Done
A7: A3 | B7: Done · v13 | C7: Performance | D7: Move 3 legal modals to on-demand /legal-modals.html | E7: Removed 860 KB of duplicated markup; homepage HTML -38% | F7: Claude | G7: 2 | H7: P1 | I7: Done
A8: A4 | B8: Done · v13 | C8: Performance | D8: Lazy-load 26 non-hero images; 1 eager hero per page | E8: Frees bandwidth for the LCP element on mobile | F8: Claude | G8: 1 | H8: P1 | I8: Done
A9: A5 | B9: Done · v13 | C9: Performance | D9: Add intrinsic width/height to images missing them | E9: Prevents cumulative layout shift | F9: Claude | G9: 0.5 | H9: P2 | I9: Done
A10: A6 | B10: Done · v13 | C10: Performance | D10: Generate responsive variants + srcset for 5 heavy images | E10: Phones stop downloading 1600px imagery | F10: Claude | G10: 1.5 | H10: P1 | I10: Done
A11: A7 | B11: Done · v13 | C11: Analytics | D11: Build track.js and wire all 8 conversion events | E11: You could not previously see which tool produces leads | F11: Claude | G11: 3 | H11: P1 | I11: Done
A12: A8 | B12: Done · v13 | C12: SEO | D12: Trim 7 pages' titles/descriptions into best-practice range | E12: All 30 indexable pages now compliant | F12: Claude | G12: 1 | H12: P2 | I12: Done
A13: A9 | B13: Done · v13 | C13: Resilience | D13: Lead rescue path: retry + email/webhook on sheet failure | E13: A failed sheet write no longer silently loses the enquiry | F13: Claude | G13: 2 | H13: P1 | I13: Done
A14: A10 | B14: Done · v13 | C14: Code quality | D14: Replace raw control bytes in security.js with escapes | E14: Invisible characters in source can be mangled by any tool | F14: Claude | G14: 0.3 | H14: P3 | I14: Done
A15: A11 | B15: Done · v13 | C15: Ops | D15: Write the operations runbook | E15: Removes key-person dependency during an incident | F15: Claude | G15: 2 | H15: P1 | I15: Done
A16: B1 | B16: H1 · Stabilise | C16: AI continuity | D16: Move off free Gemini quota, or add a failover key | E16: TOP RISK. Concierge dies at peak enquiry hours; already seen in production | F16: You | G16: 1 | H16: P1 | I16: In progress | J16: two distinct models live; still one provider + one key
A17: B2 | B17: H1 · Stabilise | C17: Ops | D17: Add uptime monitoring on / and /api/health | E17: Today you learn the site is down from a customer | F17: You | G17: 1 | H17: P1 | I17: In progress | J17: /api/monitor live + daily cron; add cron-job.org for 5-min checks
A18: B3 | B18: H1 · Stabilise | C18: Ops | D18: Add browser error tracking (Sentry free tier) | E18: JavaScript errors in real browsers are currently invisible | F18: You | G18: 1.5 | H18: P1 | I18: Done | J18: report_endpoint:true; alert email received
A19: B4 | B19: H1 · Stabilise | C19: Resilience | D19: Set ALERT_EMAIL_TO + RESCUE_WEBHOOK_URL in Vercel | E19: Activates the rescue path built in A9 — it is inert without these | F19: You | G19: 0.3 | H19: P1 | I19: Done | J19: routed via Apps Script relay; testAlerts confirmed
A20: B5 | B20: H1 · Stabilise | C20: Deploy | D20: Deploy build v13 and verify the ?v= bumps took effect | E20: Stale CDN copies are invisible failures | F20: You | G20: 0.5 | H20: P1 | I20: Done | J20: v18 live; verified by asset probe
A21: B6 | B21: H1 · Stabilise | C21: AI | D21: Turn on the chat log endpoint | E21: You cannot improve what you cannot see | F21: You | G21: 0.5 | H21: P1 | I21: Done | J21: chat_log_endpoint:true confirmed live
A22: B7 | B22: H1 · Stabilise | C22: Ops | D22: Run checkSender + sendTestEmail, publish a New Version | E22: Apps Script edits do not go live until a new version is published | F22: You | G22: 0.5 | H22: P1 | I22: Not started
A23: B8 | B23: H1 · Stabilise | C23: Analytics | D23: Create the 8 events as GA4 conversions in GTM | E23: Events fire but are not yet registered as conversions | F23: You | G23: 1 | H23: P2 | I23: Not started | J23: A7
A24: C1 | B24: H2 · Instrument | C24: Performance | D24: Run PageSpeed Insights; record real Core Web Vitals | E24: Replaces my projection with measured field data | F24: You | G24: 0.5 | H24: P1 | I24: Done | J24: mobile 71 / desktop 93; LCP 5.3s mobile
A25: C2 | B25: H2 · Instrument | C25: SEO | D25: Pull Search Console impressions, position, coverage | E25: Establishes the organic baseline this audit could not verify | F25: You | G25: 1 | H25: P1 | I25: Not started
A26: C3 | B26: H2 · Instrument | C26: SEO | D26: Check referring domains (Ahrefs free authority checker) | E26: Authority, not markup, is your binding SEO constraint | F26: You | G26: 0.5 | H26: P1 | I26: Not started
A27: C4 | B27: H2 · Instrument | C27: AI | D27: Review chat transcripts weekly; log recurring questions | E27: Buyer questions are free market research | F27: You | G27: 1 | H27: P2 | I27: Not started | J27: B6
A28: C5 | B28: H2 · Instrument | C28: Accessibility | D28: axe DevTools pass + manual screen-reader check | E28: Automated layer is clean; lets you claim WCAG 2.1 AA with confidence | F28: You | G28: 3 | H28: P2 | I28: In progress | J28: Skip links 46/46 done; manual screen-reader pass still open
A29: C6 | B29: H2 · Instrument | C29: Compliance | D29: Have an Indian privacy practitioner review DPDPA consent | E29: Itemised notice + documented erasure process are required | F29: Counsel | G29: 4 | H29: P1 | I29: Not started
A30: C7 | B30: H2 · Instrument | C30: Resilience | D30: Weekly automated backup of the Leads sheet | E30: Currently Google durability only; no independent copy | F30: You | G30: 1.5 | H30: P2 | I30: In progress | J30: IDs filled in; run backupLeads() once + add the weekly trigger
A31: C8 | B31: H2 · Instrument | C31: Performance | D31: Convert remaining legacy JPG/PNG files to WebP | E31: Typically 25-35% smaller at equal quality | F31: You | G31: 2 | H31: P3 | I31: Done | J31: 4 of 7 converted; 3 refused (WebP was larger)
A32: D1 | B32: H3 · Compound | C32: Engineering | D32: Minimal build step with content-hashed asset filenames | E32: Permanently ends the manual ?v= fragility | F32: Dev | G32: 8 | H32: P2 | I32: Done | J32: stamp-assets.mjs + build.py path bug fixed
A33: D2 | B33: H3 · Compound | C33: Engineering | D33: Smoke tests on Vercel preview deploys | E33: Nothing currently stops a broken deploy reaching production | F33: Dev | G33: 8 | H33: P2 | I33: Done | J33: 36 tests passing, desktop + mobile
A34: D3 | B34: H3 · Compound | C34: Channels | D34: Activate WhatsApp Business API (scaffolding already built) | E34: Where Indian buyers actually converse; same brain | F34: You | G34: 6 | H34: P2 | I34: Not started | J34: Scaffolding built; needs Meta credentials
A35: D4 | B35: H3 · Compound | C35: Growth | D35: Portal listings + digital PR: first 20 referring domains | E35: The single biggest lever on organic visibility | F35: You | G35: 20 | H35: P1 | I35: In progress | J35: Authority plan delivered; outreach is yours
A36: D5 | B36: H3 · Compound | C36: Content | D36: Publish pages answering the top chat questions | E36: Content that earns links because it answers real demand | F36: You | G36: 12 | H36: P2 | I36: Not started | J36: C4
A37: D6 | B37: H3 · Compound | C37: Sales | D37: Staff the human handoff console | E37: Routing exists; nobody is behind it | F37: You | G37: 4 | H37: P2 | I37: Not started
A38: D7 | B38: H3 · Compound | C38: Security | D38: Migrate CSP from 'unsafe-inline' to nonce-based | E38: Closes the last real softness in an otherwise strong policy | F38: Dev | G38: 6 | H38: P2 | I38: Not started | J38: D1
A39: D8 | B39: H3 · Compound | C39: Ops | D39: Dependency scanning (Dependabot / npm audit in CI) | E39: Vulnerable libraries currently go unnoticed | F39: Dev | G39: 2 | H39: P3 | I39: Done | J39: CI audit job + Dependabot

Sheet Scorecard
A1: Audit Scorecard — current vs. target
A2: Current scores are from the July 2026 audit. Target is what closing the roadmap should achieve. Update 'Current' after you re-audit.
A4: Category | B4: Weight % | C4: Current | D4: Target | E4: Gap | F4: What closes the gap
A5: Innovation & differentiation | B5: 0.04 | C5: 93 | D5: 95 | E5: =D5-C5 | F5: Already category-leading; maintain
A6: AI readiness | B6: 0.1 | C6: 93 | D6: 96 | E6: =D6-C6 | F6: Paid quota / failover ends the fragility (B1)
A7: SEO & discoverability | B7: 0.1 | C7: 90 | D7: 93 | E7: =D7-C7 | F7: Authority work: referring domains (D4)
A8: Security posture | B8: 0.12 | C8: 86 | D8: 93 | E8: =D8-C8 | F8: Nonce-based CSP (D7); DPDPA review (C6)
A9: UX & accessibility | B9: 0.08 | C9: 88 | D9: 92 | E9: =D9-C9 | F9: Manual a11y pass + skip links (C5)
A10: Website health | B10: 0.08 | C10: 92 | D10: 95 | E10: =D10-C10 | F10: CORRECTED: a CI gate was already present; 36 tests now green
A11: Scalability & cost | B11: 0.06 | C11: 83 | D11: 88 | E11: =D11-C11 | F11: AI quota is the only real ceiling (B1)
A12: Conversion architecture | B12: 0.1 | C12: 80 | D12: 88 | E12: =D12-C12 | F12: Events now firing (A7); register conversions (B8)
A13: Technology maturity | B13: 0.1 | C13: 90 | D13: 93 | E13: =D13-C13 | F13: CORRECTED: build.py, CI and tests already existed; audit understated this
A14: Performance | B14: 0.1 | C14: 75 | D14: 86 | E14: =D14-C14 | F14: Legal modals + lazy-load done; measure real CWV (C1)
A15: Data & analytics | B15: 0.04 | C15: 82 | D15: 88 | E15: =D15-C15 | F15: Search Console + chat logs (C2, B6)
A16: Enterprise readiness | B16: 0.08 | C16: 78 | D16: 88 | E16: =D16-C16 | F16: Monitoring, runbook, backups (B2, B3, A11, C7)
A17: COMPOSITE (weighted) | C17: =SUMPRODUCT($B$5:$B$16,C5:C16) | D17: =SUMPRODUCT($B$5:$B$16,D5:D16) | E17: =D17-C17

Sheet How to use
A1: How to use this tracker
A4: YELLOW CELLS ARE YOURS | C4: Edit only these. Everything else is a formula and will recalculate.
A5: Roadmap!F (Owner) | B5: edit | C5: Who is actually doing it.
A6: Roadmap!I (Status) | B6: edit | C6: Pick from the dropdown: Not started / In progress / Blocked / Done / Dropped.
A7: Roadmap!K (Target date) | B7: edit | C7: Your committed date.
A8: Roadmap!L (Notes) | B8: edit | C8: Anything worth remembering.
A9: Scorecard!C (Current) | B9: edit | C9: Update after you re-audit.
A11: READ-ONLY
A12: Dashboard | B12: formula | C12: Recalculates from Roadmap. Do not type over it.
A13: Roadmap!G (Effort) | B13: estimate | C13: Hours. Rough, but consistent across rows.
A14: Roadmap!J (Blocked by) | B14: reference | C14: The ID that must finish first.
A16: PRIORITIES
A17: P1 | C17: Do first. Directly protects revenue or continuity.
A18: P2 | C18: Important, not urgent. Compounding value.
A19: P3 | C19: Housekeeping. Do when convenient.
A21: A NOTE ON THE 'Done · v13' ROWS | C21: Those eleven actions were completed and verified in the build delivered with this tracker. They are listed so the record is complete and so the effort figures mean something — not as work still to schedule.
A23: WHAT THIS TRACKER CANNOT TELL YOU | C23: Traffic, rankings, backlinks and real Core Web Vitals are not in here because they were never measured. Actions C1, C2 and C3 exist specifically to go and get those numbers. Until then, treat any performance or SEO figure in the audit as a projection.
